{
  "cascas": [
    {
      "id": 1,
      "nome": "Ao Leite"
    },
    {
      "id": 2,
      "nome": "Meio Amargo"
    },
    {
      "id": 3,
      "nome": "Amargo"
    },
    {
      "id": 4,
      "nome": "Branco"
    }
  ],
  "recheios": [
    {
      "id": 1,
      "nome": "Brigadeiro",
      "descricao": "Tradicional brigadeiro cremoso de chocolate"
    },
    {
      "id": 2,
      "nome": "Prestígio",
      "descricao": "Creme de coco com chocolate, uma combinação clássica"
    },
    {
      "id": 3,
      "nome": "Ninho com Nutella",
      "descricao": "Mistura cremosa de leite ninho com nutella"
    },
    {
      "id": 4,
      "nome": "Cupuaçu com Castanha do Pará",
      "descricao": "Creme de cupuaçu com pedaços de castanha do pará"
    },
    {
      "id": 5,
      "nome": "Casadinho",
      "descricao": "Doce de leite cremoso com chocolate branco"
    },
    {
      "id": 6,
      "nome": "Oreo",
      "descricao": "Creme de baunilha com pedaços de biscoito Oreo"
    },
    {
      "id": 7,
      "nome": "Doce de Leite com Amendoim",
      "descricao": "Doce de leite cremoso com pedaços crocantes de amendoim"
    },
    {
      "id": 8,
      "nome": "Ovomaltine",
      "descricao": "Creme maltado com pedaços crocantes de Ovomaltine"
    },
    {
      "id": 9,
      "nome": "Cupulate",
      "descricao": "Creme de cupulate (chocolate e cupuaçu)"
    },
    {
      "id": 10,
      "nome": "Frango",
      "descricao": "Delicioso recheio de frango e 9 coxinhas de frango"
    }
   
  ],
  "tamanhos": [
    {
      "id": 1,
      "nome": "Mini ovo 50g",
      "tipo": "individual",
      "preco": 17.00,
      "imagem": "/img/ovos/50gmini.jpeg",
      "descricao": "Pequeno ovo de Páscoa individual, perfeito para presentear"
    },
    {
      "id": 6,
      "nome": "Ovo salgado 500g",
      "tipo": "individual",
      "preco": 65.00,
      "imagem": "/img/ovos/salgado500g.jpeg",
      "descricao": "Ovo de Páscoa salgado premium, ideal para quem prefere salgado"
    },
    {
      "id": 7,
      "nome": "Mini Caixa flork",
      "tipo": "individual",
      "preco": 19.00,
      "imagem": "/img/ovos/folk.jpeg",
      "descricao": "Caixinha decorativa com mini ovo de Páscoa, perfeita para presentear"
    },
    {
      "id": 8,
      "nome": "Controle 90g",
      "tipo": "individual",
      "preco": 58.00,
      "imagem": "/img/ovos/controlecombrigadeiro.jpeg",
      "descricao": "Ovo no formato de videogame, divertido e delicioso para os gamers"
    }
  ],
  "pacotes": [
    {
      "id": 2,
      "nome": "Trio Mini - 3 ovos de 50g",
      "tipo": "pacote",
      "descricao": "Pacote com 3 mini ovos de 50g cada",
      "quantidade": 3,
      "gramasIndividual": 50,
      "gramasTotal": 150,
      "preco": 48.00,
      "imagem": "/img/ovos/triomini.jpeg"
    },
    {
      "id": 3,
      "nome": "Quarteto Mini - 4 ovos de 50g",
      "tipo": "pacote",
      "descricao": "Pacote com 4 mini ovos de 50g cada",
      "quantidade": 4,
      "gramasIndividual": 50,
      "gramasTotal": 200,
      "preco": 60.00,
      "imagem": "/img/ovos/quartetomini.jpeg"
    },
    {
      "id": 4,
      "nome": "Mini Box - 6 ovos de 50g",
      "tipo": "pacote",
      "descricao": "Caixa com 6 mini ovos de 50g cada",
      "quantidade": 6,
      "gramasIndividual": 50,
      "gramasTotal": 300,
      "preco": 70.00,
      "imagem": "/img/ovos/6miniovos.jpeg"
    },
    {
      "id": 5,
      "nome": "Dupla - 2 ovos de 150g",
      "tipo": "pacote",
      "descricao": "Caixa com 2 ovos de 150g cada",
      "quantidade": 2,
      "gramasIndividual": 150,
      "gramasTotal": 300,
      "preco": 70.00,
      "imagem": "/img/ovos/dupla150g.jpeg"
    },
    {
      "id": 9,
      "nome": "Kit confeiteiro",
      "tipo": "pacote",
      "descricao": "Caixa com 5 mini ovos de 50g ou 1 ovo de 250g",
      "quantidade": 2,
      "gramasIndividual": 250,
      "gramasTotal": 300,
      "preco": 85.00,
      "imagem": "/img/ovos/kiteconfeiterio.jpeg"
    }
  ]
}